setup.py
semaphore_client/__init__.py
semaphore_client/api_client.py
semaphore_client/configuration.py
semaphore_client/exceptions.py
semaphore_client/model_utils.py
semaphore_client/rest.py
semaphore_client/apis/__init__.py
semaphore_client/model/__init__.py
semaphore_client/model/access_key.py
semaphore_client/model/access_key_request.py
semaphore_client/model/api_token.py
semaphore_client/model/environment.py
semaphore_client/model/environment_request.py
semaphore_client/model/event.py
semaphore_client/model/info_type.py
semaphore_client/model/info_type_update.py
semaphore_client/model/inventory.py
semaphore_client/model/inventory_request.py
semaphore_client/model/login.py
semaphore_client/model/project.py
semaphore_client/model/project_project_id_delete_request.py
semaphore_client/model/project_project_id_tasks_get_request.py
semaphore_client/model/project_project_id_users_get_request.py
semaphore_client/model/project_request.py
semaphore_client/model/repository.py
semaphore_client/model/repository_request.py
semaphore_client/model/schedule.py
semaphore_client/model/schedule_request.py
semaphore_client/model/task.py
semaphore_client/model/task_output.py
semaphore_client/model/template.py
semaphore_client/model/template_request.py
semaphore_client/model/user.py
semaphore_client/model/user_put_request.py
semaphore_client/model/user_request.py
semaphore_client/model/users_user_id_password_post_request.py
semaphore_client/model/view.py
semaphore_client/model/view_request.py
semaphore_client/models/__init__.py
semaphore_client/semaphore/__init__.py
semaphore_client/semaphore/authentication_api.py
semaphore_client/semaphore/default_api.py
semaphore_client/semaphore/project_api.py
semaphore_client/semaphore/projects_api.py
semaphore_client/semaphore/schedule_api.py
semaphore_client/semaphore/user_api.py
ansible_semaphore_client-0.0.2.dist-info/METADATA
ansible_semaphore_client-0.0.2.dist-info/WHEEL
ansible_semaphore_client-0.0.2.dist-info/licenses/LICENSE
ansible_semaphore_client-0.0.2.dist-info/RECORD
