Metadata-Version: 2.1
Name: ansible-semaphore-client
Version: 0.0.2
Summary: Ansible Semaphore client library
Project-URL: Homepage, https://github.com/VitexSoftware/libpython-semaphore-client
Project-URL: Bug Tracker, https://github.com/VitexSoftware/libpython-semaphore-client/issues
Author-email: Vítězslav Dvořák <info@vitexsoftware.com>
License: MIT License
License-File: LICENSE
Classifier: License :: OSI Approved :: MIT License
Classifier: Operating System :: OS Independent
Classifier: Programming Language :: Python :: 3
Requires-Python: >=3.7
Requires-Dist: python-dateutil
Requires-Dist: urllib3
